{"__typename":"PlayByPlay","contestId":6261288,"title":"WSB PLAY-BY-PLAY","description":"Binghamton vs UMass Lowell","divisionName":"d1","status":"final","period":5,"minutes":"","seconds":"","teams":[{"__typename":"ContestTeam","isHome":true,"teamId":"42497","seoname":"binghamton","name6Char":"BINGHA","nameShort":"Binghamton","nameFull":"Binghamton University","teamName":"Bearcats","color":"#006747"},{"__typename":"ContestTeam","isHome":false,"teamId":"42359","seoname":"umass-lowell","name6Char":"UMASSL","nameShort":"UMass Lowell","nameFull":"University of Massachusetts Lowell","teamName":"River Hawks","color":"#003DA5"}],"periods":[{"__typename":"PlayByPlayDetails","periodNumber":1,"periodDisplay":"1st","playbyplayStats":[{"__typename":"PlayByPlayGenericSport","clock":"","teamId":42359,"plays":[{"__typename":"GenericPlay","playText":"Batting starts","homeScore":null,"visitorScore":null,"clock":""}]},{"__typename":"PlayByPlayGenericSport","clock":"","teamId":42359,"plays":[{"__typename":"GenericPlay","playText":"L. WHITE flied out to cf.","homeScore":null,"visitorScore":null,"clock":""}]},{"__typename":"PlayByPlayGenericSport","clock":"","teamId":42359,"plays":[{"__typename":"GenericPlay","playText":"DAVENPORT walked.","homeScore":null,"visitorScore":null,"clock":""}]},{"__typename":"PlayByPlayGenericSport","clock":"","teamId":42359,"plays":[{"__typename":"GenericPlay","playText":"FISHER flied out to cf.","homeScore":null,"visitorScore":null,"clock":""}]},{"__typename":"PlayByPlayGenericSport","clock":"","teamId":42359,"plays":[{"__typename":"GenericPlay","playText":"FREDERICK struck out swinging.","homeScore":null,"visitorScore":null,"clock":""}]},{"__typename":"PlayByPlayGenericSport","clock":"","teamId":42359,"plays":[{"__typename":"GenericPlay","playText":"Batting ends R: 0 H:0 E:0","homeScore":0,"visitorScore":0,"clock":""}]},{"__typename":"PlayByPlayGenericSport","clock":"","teamId":42497,"plays":[{"__typename":"GenericPlay","playText":"Batting starts","homeScore":null,"visitorScore":null,"clock":""}]},{"__typename":"PlayByPlayGenericSport","clock":"","teamId":42497,"plays":[{"__typename":"GenericPlay","playText":"Santos fouled out to lf.","homeScore":null,"visitorScore":null,"clock":""}]},{"__typename":"PlayByPlayGenericSport","clock":"","teamId":42497,"plays":[{"__typename":"GenericPlay","playText":"Walter lined out to ss.","homeScore":null,"visitorScore":null,"clock":""}]},{"__typename":"PlayByPlayGenericSport","clock":"","teamId":42497,"plays":[{"__typename":"GenericPlay","playText":"L'Amoreaux singled to center field.","homeScore":null,"visitorScore":null,"clock":""}]},{"__typename":"PlayByPlayGenericSport","clock":"","teamId":42497,"plays":[{"__typename":"GenericPlay","playText":"Lawson doubled to left center, RBI3a L'Amoreaux scored.","homeScore":null,"visitorScore":null,"clock":""}]},{"__typename":"PlayByPlayGenericSport","clock":"","teamId":42497,"plays":[{"__typename":"GenericPlay","playText":"Carvalho singled to shortstop.","homeScore":null,"visitorScore":null,"clock":""}]},{"__typename":"PlayByPlayGenericSport","clock":"","teamId":42497,"plays":[{"__typename":"GenericPlay","playText":"Musial doubled to right center, 2 RBI3a Carvalho scored3a Lawson scored.","homeScore":null,"visitorScore":null,"clock":""}]},{"__typename":"PlayByPlayGenericSport","clock":"","teamId":42497,"plays":[{"__typename":"GenericPlay","playText":"Musial advanced to third on a passed ball.","homeScore":null,"visitorScore":null,"clock":""}]},{"__typename":"PlayByPlayGenericSport","clock":"","teamId":42497,"plays":[{"__typename":"GenericPlay","playText":"Farina walked.","homeScore":null,"visitorScore":null,"clock":""}]},{"__typename":"PlayByPlayGenericSport","clock":"","teamId":42497,"plays":[{"__typename":"GenericPlay","playText":"Dodig singled to right field, RBI3a Farina advanced to second3a Musial scored.","homeScore":null,"visitorScore":null,"clock":""}]},{"__typename":"PlayByPlayGenericSport","clock":"","teamId":42497,"plays":[{"__typename":"GenericPlay","playText":"Guerrero singled, RBI3a Dodig advanced to second3a Farina scored.","homeScore":null,"visitorScore":null,"clock":""}]},{"__typename":"PlayByPlayGenericSport","clock":"","teamId":42359,"plays":[{"__typename":"GenericPlay","playText":"DECITISE to p for SLANOVEC.","homeScore":null,"visitorScore":null,"clock":""}]},{"__typename":"PlayByPlayGenericSport","clock":"","teamId":42497,"plays":[{"__typename":"GenericPlay","playText":"Santos grounded out to 1b unassisted.","homeScore":null,"visitorScore":null,"clock":""}]},{"__typename":"PlayByPlayGenericSport","clock":"","teamId":42497,"plays":[{"__typename":"GenericPlay","playText":"Batting ends R: 5 H:6 E:0","homeScore":5,"visitorScore":0,"clock":""}]}]},{"__typename":"PlayByPlayDetails","periodNumber":2,"periodDisplay":"2nd","playbyplayStats":[{"__typename":"PlayByPlayGenericSport","clock":"","teamId":42359,"plays":[{"__typename":"GenericPlay","playText":"Batting starts","homeScore":null,"visitorScore":null,"clock":""}]},{"__typename":"PlayByPlayGenericSport","clock":"","teamId":42359,"plays":[{"__typename":"GenericPlay","playText":"FITZGERALD grounded out to 2b.","homeScore":null,"visitorScore":null,"clock":""}]},{"__typename":"PlayByPlayGenericSport","clock":"","teamId":42359,"plays":[{"__typename":"GenericPlay","playText":"SANTIAGO homered to right field, RBI.","homeScore":null,"visitorScore":null,"clock":""}]},{"__typename":"PlayByPlayGenericSport","clock":"","teamId":42359,"plays":[{"__typename":"GenericPlay","playText":"TOW struck out swinging.","homeScore":null,"visitorScore":null,"clock":""}]},{"__typename":"PlayByPlayGenericSport","clock":"","teamId":42359,"plays":[{"__typename":"GenericPlay","playText":"TULLEY struck out swinging.","homeScore":null,"visitorScore":null,"clock":""}]},{"__typename":"PlayByPlayGenericSport","clock":"","teamId":42359,"plays":[{"__typename":"GenericPlay","playText":"Batting ends R: 1 H:1 E:0","homeScore":5,"visitorScore":1,"clock":""}]},{"__typename":"PlayByPlayGenericSport","clock":"","teamId":42497,"plays":[{"__typename":"GenericPlay","playText":"Batting starts","homeScore":null,"visitorScore":null,"clock":""}]},{"__typename":"PlayByPlayGenericSport","clock":"","teamId":42359,"plays":[{"__typename":"GenericPlay","playText":"FISHER to dh.","homeScore":null,"visitorScore":null,"clock":""}]},{"__typename":"PlayByPlayGenericSport","clock":"","teamId":42359,"plays":[{"__typename":"GenericPlay","playText":"NEELD to rf for TOW.","homeScore":null,"visitorScore":null,"clock":""}]},{"__typename":"PlayByPlayGenericSport","clock":"","teamId":42359,"plays":[{"__typename":"GenericPlay","playText":"SANTIAGO to c.","homeScore":null,"visitorScore":null,"clock":""}]},{"__typename":"PlayByPlayGenericSport","clock":"","teamId":42359,"plays":[{"__typename":"GenericPlay","playText":"NEELD to 3b.","homeScore":null,"visitorScore":null,"clock":""}]},{"__typename":"PlayByPlayGenericSport","clock":"","teamId":42359,"plays":[{"__typename":"GenericPlay","playText":"SANTOLI to rf.","homeScore":null,"visitorScore":null,"clock":""}]},{"__typename":"PlayByPlayGenericSport","clock":"","teamId":42497,"plays":[{"__typename":"GenericPlay","playText":"Walter struck out swinging.","homeScore":null,"visitorScore":null,"clock":""}]},{"__typename":"PlayByPlayGenericSport","clock":"","teamId":42497,"plays":[{"__typename":"GenericPlay","playText":"L'Amoreaux flied out to cf.","homeScore":null,"visitorScore":null,"clock":""}]},{"__typename":"PlayByPlayGenericSport","clock":"","teamId":42497,"plays":[{"__typename":"GenericPlay","playText":"Lawson grounded out to ss.","homeScore":null,"visitorScore":null,"clock":""}]},{"__typename":"PlayByPlayGenericSport","clock":"","teamId":42497,"plays":[{"__typename":"GenericPlay","playText":"Batting ends R: 0 H:0 E:0","homeScore":5,"visitorScore":1,"clock":""}]}]},{"__typename":"PlayByPlayDetails","periodNumber":3,"periodDisplay":"3rd","playbyplayStats":[{"__typename":"PlayByPlayGenericSport","clock":"","teamId":42359,"plays":[{"__typename":"GenericPlay","playText":"Batting starts","homeScore":null,"visitorScore":null,"clock":""}]},{"__typename":"PlayByPlayGenericSport","clock":"","teamId":42359,"plays":[{"__typename":"GenericPlay","playText":"SANTOLI walked.","homeScore":null,"visitorScore":null,"clock":""}]},{"__typename":"PlayByPlayGenericSport","clock":"","teamId":42359,"plays":[{"__typename":"GenericPlay","playText":"L. WHITE flied out to rf.","homeScore":null,"visitorScore":null,"clock":""}]},{"__typename":"PlayByPlayGenericSport","clock":"","teamId":42359,"plays":[{"__typename":"GenericPlay","playText":"DAVENPORT popped up to 1b.","homeScore":null,"visitorScore":null,"clock":""}]},{"__typename":"PlayByPlayGenericSport","clock":"","teamId":42359,"plays":[{"__typename":"GenericPlay","playText":"FISHER flied out to rf.","homeScore":null,"visitorScore":null,"clock":""}]},{"__typename":"PlayByPlayGenericSport","clock":"","teamId":42359,"plays":[{"__typename":"GenericPlay","playText":"Batting ends R: 0 H:0 E:0","homeScore":5,"visitorScore":1,"clock":""}]},{"__typename":"PlayByPlayGenericSport","clock":"","teamId":42497,"plays":[{"__typename":"GenericPlay","playText":"Batting starts","homeScore":null,"visitorScore":null,"clock":""}]},{"__typename":"PlayByPlayGenericSport","clock":"","teamId":42497,"plays":[{"__typename":"GenericPlay","playText":"Carvalho grounded out to 3b.","homeScore":null,"visitorScore":null,"clock":""}]},{"__typename":"PlayByPlayGenericSport","clock":"","teamId":42497,"plays":[{"__typename":"GenericPlay","playText":"Musial popped up to p.","homeScore":null,"visitorScore":null,"clock":""}]},{"__typename":"PlayByPlayGenericSport","clock":"","teamId":42497,"plays":[{"__typename":"GenericPlay","playText":"Farina struck out swinging.","homeScore":null,"visitorScore":null,"clock":""}]},{"__typename":"PlayByPlayGenericSport","clock":"","teamId":42497,"plays":[{"__typename":"GenericPlay","playText":"Batting ends R: 0 H:0 E:0","homeScore":5,"visitorScore":1,"clock":""}]}]},{"__typename":"PlayByPlayDetails","periodNumber":4,"periodDisplay":"4th","playbyplayStats":[{"__typename":"PlayByPlayGenericSport","clock":"","teamId":42359,"plays":[{"__typename":"GenericPlay","playText":"Batting starts","homeScore":null,"visitorScore":null,"clock":""}]},{"__typename":"PlayByPlayGenericSport","clock":"","teamId":42359,"plays":[{"__typename":"GenericPlay","playText":"FREDERICK struck out swinging.","homeScore":null,"visitorScore":null,"clock":""}]},{"__typename":"PlayByPlayGenericSport","clock":"","teamId":42359,"plays":[{"__typename":"GenericPlay","playText":"FITZGERALD singled to left field.","homeScore":null,"visitorScore":null,"clock":""}]},{"__typename":"PlayByPlayGenericSport","clock":"","teamId":42359,"plays":[{"__typename":"GenericPlay","playText":"SANTIAGO hit by pitch3a FITZGERALD advanced to second.","homeScore":null,"visitorScore":null,"clock":""}]},{"__typename":"PlayByPlayGenericSport","clock":"","teamId":42359,"plays":[{"__typename":"GenericPlay","playText":"NEELD popped up to ss.","homeScore":null,"visitorScore":null,"clock":""}]},{"__typename":"PlayByPlayGenericSport","clock":"","teamId":42359,"plays":[{"__typename":"GenericPlay","playText":"TULLEY struck out swinging.","homeScore":null,"visitorScore":null,"clock":""}]},{"__typename":"PlayByPlayGenericSport","clock":"","teamId":42359,"plays":[{"__typename":"GenericPlay","playText":"Batting ends R: 0 H:1 E:0","homeScore":5,"visitorScore":1,"clock":""}]},{"__typename":"PlayByPlayGenericSport","clock":"","teamId":42497,"plays":[{"__typename":"GenericPlay","playText":"Batting starts","homeScore":null,"visitorScore":null,"clock":""}]},{"__typename":"PlayByPlayGenericSport","clock":"","teamId":42497,"plays":[{"__typename":"GenericPlay","playText":"Dodig singled to right field.","homeScore":null,"visitorScore":null,"clock":""}]},{"__typename":"PlayByPlayGenericSport","clock":"","teamId":42497,"plays":[{"__typename":"GenericPlay","playText":"Guerrero singled to left field3a Dodig advanced to second.","homeScore":null,"visitorScore":null,"clock":""}]},{"__typename":"PlayByPlayGenericSport","clock":"","teamId":42497,"plays":[{"__typename":"GenericPlay","playText":"Santos singled to right field3a Guerrero advanced to second3a Dodig advanced to third.","homeScore":null,"visitorScore":null,"clock":""}]},{"__typename":"PlayByPlayGenericSport","clock":"","teamId":42497,"plays":[{"__typename":"GenericPlay","playText":"Levine pinch hit for Walter.","homeScore":null,"visitorScore":null,"clock":""}]},{"__typename":"PlayByPlayGenericSport","clock":"","teamId":42497,"plays":[{"__typename":"GenericPlay","playText":"Levine walked, RBI3a Santos advanced to second3a Guerrero advanced to third3a Dodig scored.","homeScore":null,"visitorScore":null,"clock":""}]},{"__typename":"PlayByPlayGenericSport","clock":"","teamId":42497,"plays":[{"__typename":"GenericPlay","playText":"Walter to lf for Levine.","homeScore":null,"visitorScore":null,"clock":""}]},{"__typename":"PlayByPlayGenericSport","clock":"","teamId":42497,"plays":[{"__typename":"GenericPlay","playText":"L'Amoreaux hit by pitch, RBI3a Walter advanced to second3a Santos advanced to third3a Guerrero scored.","homeScore":null,"visitorScore":null,"clock":""}]},{"__typename":"PlayByPlayGenericSport","clock":"","teamId":42497,"plays":[{"__typename":"GenericPlay","playText":"Lawson singled to left field, RBI3a L'Amoreaux advanced to second3a Walter advanced to third3a Santos scored.","homeScore":null,"visitorScore":null,"clock":""}]},{"__typename":"PlayByPlayGenericSport","clock":"","teamId":42497,"plays":[{"__typename":"GenericPlay","playText":"Carvalho popped up to 2b.","homeScore":null,"visitorScore":null,"clock":""}]},{"__typename":"PlayByPlayGenericSport","clock":"","teamId":42497,"plays":[{"__typename":"GenericPlay","playText":"Musial singled, RBI3a Lawson advanced to second3a L'Amoreaux scored3a Walter scored.","homeScore":null,"visitorScore":null,"clock":""}]},{"__typename":"PlayByPlayGenericSport","clock":"","teamId":42359,"plays":[{"__typename":"GenericPlay","playText":"SLANOVEC to p for DECITISE.","homeScore":null,"visitorScore":null,"clock":""}]},{"__typename":"PlayByPlayGenericSport","clock":"","teamId":42497,"plays":[{"__typename":"GenericPlay","playText":"Farina singled3a Musial advanced to second3a Lawson advanced to third.","homeScore":null,"visitorScore":null,"clock":""}]},{"__typename":"PlayByPlayGenericSport","clock":"","teamId":42497,"plays":[{"__typename":"GenericPlay","playText":"Minnichbach pinch ran for Musial.","homeScore":null,"visitorScore":null,"clock":""}]},{"__typename":"PlayByPlayGenericSport","clock":"","teamId":42497,"plays":[{"__typename":"GenericPlay","playText":"Fittry pinch hit for Dodig.","homeScore":null,"visitorScore":null,"clock":""}]},{"__typename":"PlayByPlayGenericSport","clock":"","teamId":42497,"plays":[{"__typename":"GenericPlay","playText":"Fittry hit into double play 2b to 1b3a Farina out on the play.","homeScore":null,"visitorScore":null,"clock":""}]},{"__typename":"PlayByPlayGenericSport","clock":"","teamId":42497,"plays":[{"__typename":"GenericPlay","playText":"Batting ends R: 5 H:6 E:0","homeScore":10,"visitorScore":1,"clock":""}]}]},{"__typename":"PlayByPlayDetails","periodNumber":5,"periodDisplay":"5th","playbyplayStats":[{"__typename":"PlayByPlayGenericSport","clock":"","teamId":42359,"plays":[{"__typename":"GenericPlay","playText":"Batting starts","homeScore":null,"visitorScore":null,"clock":""}]},{"__typename":"PlayByPlayGenericSport","clock":"","teamId":42497,"plays":[{"__typename":"GenericPlay","playText":"Musial to 1b for Minnichbach.","homeScore":null,"visitorScore":null,"clock":""}]},{"__typename":"PlayByPlayGenericSport","clock":"","teamId":42497,"plays":[{"__typename":"GenericPlay","playText":"Dodig to 2b for Fittry.","homeScore":null,"visitorScore":null,"clock":""}]},{"__typename":"PlayByPlayGenericSport","clock":"","teamId":42359,"plays":[{"__typename":"GenericPlay","playText":"SANTOLI popped up to 2b.","homeScore":null,"visitorScore":null,"clock":""}]},{"__typename":"PlayByPlayGenericSport","clock":"","teamId":42359,"plays":[{"__typename":"GenericPlay","playText":"L. WHITE homered to left field, RBI.","homeScore":null,"visitorScore":null,"clock":""}]},{"__typename":"PlayByPlayGenericSport","clock":"","teamId":42359,"plays":[{"__typename":"GenericPlay","playText":"DAVENPORT singled to right field.","homeScore":null,"visitorScore":null,"clock":""}]},{"__typename":"PlayByPlayGenericSport","clock":"","teamId":42359,"plays":[{"__typename":"GenericPlay","playText":"HOWES pinch hit for DAVENPORT.","homeScore":null,"visitorScore":null,"clock":""}]},{"__typename":"PlayByPlayGenericSport","clock":"","teamId":42359,"plays":[{"__typename":"GenericPlay","playText":"FISHER singled3a HOWES advanced to second.","homeScore":null,"visitorScore":null,"clock":""}]},{"__typename":"PlayByPlayGenericSport","clock":"","teamId":42497,"plays":[{"__typename":"GenericPlay","playText":"Santos to lf.","homeScore":null,"visitorScore":null,"clock":""}]},{"__typename":"PlayByPlayGenericSport","clock":"","teamId":42497,"plays":[{"__typename":"GenericPlay","playText":"Walter to p.","homeScore":null,"visitorScore":null,"clock":""}]},{"__typename":"PlayByPlayGenericSport","clock":"","teamId":42497,"plays":[{"__typename":"GenericPlay","playText":"Rende to rf for L'Amoreaux.","homeScore":null,"visitorScore":null,"clock":""}]},{"__typename":"PlayByPlayGenericSport","clock":"","teamId":42359,"plays":[{"__typename":"GenericPlay","playText":"FREDERICK reached on a fielder's choice3a FISHER out at second ss to 2b3a HOWES advanced to third.","homeScore":null,"visitorScore":null,"clock":""}]},{"__typename":"PlayByPlayGenericSport","clock":"","teamId":42359,"plays":[{"__typename":"GenericPlay","playText":"FITZGERALD reached on a fielder's choice3a FREDERICK out at second ss to 2b.","homeScore":null,"visitorScore":null,"clock":""}]},{"__typename":"PlayByPlayGenericSport","clock":"","teamId":42359,"plays":[{"__typename":"GenericPlay","playText":"Batting ends R: 1 H:3 E:0","homeScore":10,"visitorScore":2,"clock":""}]}]}]}