{"__typename":"PlayByPlay","contestId":6261310,"title":"WSB PLAY-BY-PLAY","description":"Sam Houston vs Jacksonville St.","divisionName":"d1","status":"final","period":7,"minutes":"","seconds":"","teams":[{"__typename":"ContestTeam","isHome":true,"teamId":"42767","seoname":"sam-houston-st","name6Char":"SAMHOU","nameShort":"Sam Houston","nameFull":"Sam Houston State University","teamName":"Bearkats","color":"#DF502A"},{"__typename":"ContestTeam","isHome":false,"teamId":"41871","seoname":"jacksonville-st","name6Char":"JAX ST","nameShort":"Jacksonville St.","nameFull":"Jacksonville State University","teamName":"Gamecocks","color":"#C8102E"}],"periods":[{"__typename":"PlayByPlayDetails","periodNumber":1,"periodDisplay":"1st","playbyplayStats":[{"__typename":"PlayByPlayGenericSport","clock":"","teamId":41871,"plays":[{"__typename":"GenericPlay","playText":"Batting starts","homeScore":null,"visitorScore":null,"clock":""}]},{"__typename":"PlayByPlayGenericSport","clock":"","teamId":41871,"plays":[{"__typename":"GenericPlay","playText":"NICHOLSON, K grounded out to ss (2-2 BBKF).","homeScore":null,"visitorScore":null,"clock":""}]},{"__typename":"PlayByPlayGenericSport","clock":"","teamId":41871,"plays":[{"__typename":"GenericPlay","playText":"JONES, E. grounded out to 2b (2-2 BSBK).","homeScore":null,"visitorScore":null,"clock":""}]},{"__typename":"PlayByPlayGenericSport","clock":"","teamId":41871,"plays":[{"__typename":"GenericPlay","playText":"NOWAKOWSKI,M singled through the right side (0-0).","homeScore":null,"visitorScore":null,"clock":""}]},{"__typename":"PlayByPlayGenericSport","clock":"","teamId":41871,"plays":[{"__typename":"GenericPlay","playText":"REED, A. flied out to lf (2-2 KBFB).","homeScore":null,"visitorScore":null,"clock":""}]},{"__typename":"PlayByPlayGenericSport","clock":"","teamId":41871,"plays":[{"__typename":"GenericPlay","playText":"Batting ends R: 0 H:1 E:0","homeScore":0,"visitorScore":0,"clock":""}]},{"__typename":"PlayByPlayGenericSport","clock":"","teamId":42767,"plays":[{"__typename":"GenericPlay","playText":"Batting starts","homeScore":null,"visitorScore":null,"clock":""}]},{"__typename":"PlayByPlayGenericSport","clock":"","teamId":42767,"plays":[{"__typename":"GenericPlay","playText":"Grill, E. walked (3-0 BBBB).","homeScore":null,"visitorScore":null,"clock":""}]},{"__typename":"PlayByPlayGenericSport","clock":"","teamId":42767,"plays":[{"__typename":"GenericPlay","playText":"Hebel, E. doubled to center field (1-2 KFB); Grill, E. advanced to third.","homeScore":null,"visitorScore":null,"clock":""}]},{"__typename":"PlayByPlayGenericSport","clock":"","teamId":42767,"plays":[{"__typename":"GenericPlay","playText":"Yarotsky, T. popped up to ss (0-1 K).","homeScore":null,"visitorScore":null,"clock":""}]},{"__typename":"PlayByPlayGenericSport","clock":"","teamId":42767,"plays":[{"__typename":"GenericPlay","playText":"Herzinger flied out to lf, SF, RBI (1-1 KB); Grill, E. scored.","homeScore":null,"visitorScore":null,"clock":""}]},{"__typename":"PlayByPlayGenericSport","clock":"","teamId":42767,"plays":[{"__typename":"GenericPlay","playText":"Hobbs, K. popped up to 2b (2-2 KBFB).","homeScore":null,"visitorScore":null,"clock":""}]},{"__typename":"PlayByPlayGenericSport","clock":"","teamId":42767,"plays":[{"__typename":"GenericPlay","playText":"Batting ends R: 1 H:1 E:0","homeScore":1,"visitorScore":0,"clock":""}]}]},{"__typename":"PlayByPlayDetails","periodNumber":2,"periodDisplay":"2nd","playbyplayStats":[{"__typename":"PlayByPlayGenericSport","clock":"","teamId":41871,"plays":[{"__typename":"GenericPlay","playText":"Batting starts","homeScore":null,"visitorScore":null,"clock":""}]},{"__typename":"PlayByPlayGenericSport","clock":"","teamId":41871,"plays":[{"__typename":"GenericPlay","playText":"RASMUSSEN M grounded out to 3b (1-2 KKB).","homeScore":null,"visitorScore":null,"clock":""}]},{"__typename":"PlayByPlayGenericSport","clock":"","teamId":41871,"plays":[{"__typename":"GenericPlay","playText":"KYSER, M. singled through the right side (2-2 BSSBF).","homeScore":null,"visitorScore":null,"clock":""}]},{"__typename":"PlayByPlayGenericSport","clock":"","teamId":41871,"plays":[{"__typename":"GenericPlay","playText":"KYSER, M. advanced to second on a wild pitch.","homeScore":null,"visitorScore":null,"clock":""}]},{"__typename":"PlayByPlayGenericSport","clock":"","teamId":41871,"plays":[{"__typename":"GenericPlay","playText":"BUFFINGTON,H walked (3-2 BBBKKFFB).","homeScore":null,"visitorScore":null,"clock":""}]},{"__typename":"PlayByPlayGenericSport","clock":"","teamId":41871,"plays":[{"__typename":"GenericPlay","playText":"PHILLIPS, A. struck out swinging (1-2 FKBFS).","homeScore":null,"visitorScore":null,"clock":""}]},{"__typename":"PlayByPlayGenericSport","clock":"","teamId":41871,"plays":[{"__typename":"GenericPlay","playText":"PATE, E. fouled out to 1b (1-0 B).","homeScore":null,"visitorScore":null,"clock":""}]},{"__typename":"PlayByPlayGenericSport","clock":"","teamId":41871,"plays":[{"__typename":"GenericPlay","playText":"Batting ends R: 0 H:1 E:0","homeScore":1,"visitorScore":0,"clock":""}]},{"__typename":"PlayByPlayGenericSport","clock":"","teamId":42767,"plays":[{"__typename":"GenericPlay","playText":"Batting starts","homeScore":null,"visitorScore":null,"clock":""}]},{"__typename":"PlayByPlayGenericSport","clock":"","teamId":42767,"plays":[{"__typename":"GenericPlay","playText":"Mountain, H. popped up to 2b (2-2 BKSB).","homeScore":null,"visitorScore":null,"clock":""}]},{"__typename":"PlayByPlayGenericSport","clock":"","teamId":42767,"plays":[{"__typename":"GenericPlay","playText":"Scheaffer, H flied out to rf (0-0).","homeScore":null,"visitorScore":null,"clock":""}]},{"__typename":"PlayByPlayGenericSport","clock":"","teamId":42767,"plays":[{"__typename":"GenericPlay","playText":"Hobbs, Ki. struck out swinging (3-2 BSBSFBS).","homeScore":null,"visitorScore":null,"clock":""}]},{"__typename":"PlayByPlayGenericSport","clock":"","teamId":42767,"plays":[{"__typename":"GenericPlay","playText":"Batting ends R: 0 H:0 E:0","homeScore":1,"visitorScore":0,"clock":""}]}]},{"__typename":"PlayByPlayDetails","periodNumber":3,"periodDisplay":"3rd","playbyplayStats":[{"__typename":"PlayByPlayGenericSport","clock":"","teamId":41871,"plays":[{"__typename":"GenericPlay","playText":"Batting starts","homeScore":null,"visitorScore":null,"clock":""}]},{"__typename":"PlayByPlayGenericSport","clock":"","teamId":41871,"plays":[{"__typename":"GenericPlay","playText":"NICHOLSON, K grounded out to ss (1-1 FB).","homeScore":null,"visitorScore":null,"clock":""}]},{"__typename":"PlayByPlayGenericSport","clock":"","teamId":41871,"plays":[{"__typename":"GenericPlay","playText":"JONES, E. singled down the rf line (2-1 BFB).","homeScore":null,"visitorScore":null,"clock":""}]},{"__typename":"PlayByPlayGenericSport","clock":"","teamId":41871,"plays":[{"__typename":"GenericPlay","playText":"JONES, E. stole second.","homeScore":null,"visitorScore":null,"clock":""}]},{"__typename":"PlayByPlayGenericSport","clock":"","teamId":41871,"plays":[{"__typename":"GenericPlay","playText":"NOWAKOWSKI,M singled to right field, RBI (2-2 BSBF); JONES, E. scored.","homeScore":null,"visitorScore":null,"clock":""}]},{"__typename":"PlayByPlayGenericSport","clock":"","teamId":41871,"plays":[{"__typename":"GenericPlay","playText":"REED, A. reached on a fielder's choice (2-2 KFBB); NOWAKOWSKI,M out at second 2b to ss.","homeScore":null,"visitorScore":null,"clock":""}]},{"__typename":"PlayByPlayGenericSport","clock":"","teamId":41871,"plays":[{"__typename":"GenericPlay","playText":"RASMUSSEN M grounded out to 3b (0-2 FK).","homeScore":null,"visitorScore":null,"clock":""}]},{"__typename":"PlayByPlayGenericSport","clock":"","teamId":41871,"plays":[{"__typename":"GenericPlay","playText":"Batting ends R: 1 H:2 E:0","homeScore":1,"visitorScore":1,"clock":""}]},{"__typename":"PlayByPlayGenericSport","clock":"","teamId":42767,"plays":[{"__typename":"GenericPlay","playText":"Batting starts","homeScore":null,"visitorScore":null,"clock":""}]},{"__typename":"PlayByPlayGenericSport","clock":"","teamId":42767,"plays":[{"__typename":"GenericPlay","playText":"Talbot, C. fouled out to ss (3-1 BBFB).","homeScore":null,"visitorScore":null,"clock":""}]},{"__typename":"PlayByPlayGenericSport","clock":"","teamId":42767,"plays":[{"__typename":"GenericPlay","playText":"Grill, E. singled to second base (2-2 KBBF).","homeScore":null,"visitorScore":null,"clock":""}]},{"__typename":"PlayByPlayGenericSport","clock":"","teamId":42767,"plays":[{"__typename":"GenericPlay","playText":"Hebel, E. hit by pitch (0-1 F); Grill, E. advanced to second.","homeScore":null,"visitorScore":null,"clock":""}]},{"__typename":"PlayByPlayGenericSport","clock":"","teamId":42767,"plays":[{"__typename":"GenericPlay","playText":"Carter, H. pinch ran for Hebel, E..","homeScore":null,"visitorScore":null,"clock":""}]},{"__typename":"PlayByPlayGenericSport","clock":"","teamId":42767,"plays":[{"__typename":"GenericPlay","playText":"Yarotsky, T. fouled out to 2b (0-0).","homeScore":null,"visitorScore":null,"clock":""}]},{"__typename":"PlayByPlayGenericSport","clock":"","teamId":42767,"plays":[{"__typename":"GenericPlay","playText":"Herzinger lined out to 3b (1-2 SFB).","homeScore":null,"visitorScore":null,"clock":""}]},{"__typename":"PlayByPlayGenericSport","clock":"","teamId":42767,"plays":[{"__typename":"GenericPlay","playText":"Batting ends R: 0 H:1 E:0","homeScore":1,"visitorScore":1,"clock":""}]}]},{"__typename":"PlayByPlayDetails","periodNumber":4,"periodDisplay":"4th","playbyplayStats":[{"__typename":"PlayByPlayGenericSport","clock":"","teamId":41871,"plays":[{"__typename":"GenericPlay","playText":"Batting starts","homeScore":null,"visitorScore":null,"clock":""}]},{"__typename":"PlayByPlayGenericSport","clock":"","teamId":42767,"plays":[{"__typename":"GenericPlay","playText":"Carter, H. to 2b.","homeScore":null,"visitorScore":null,"clock":""}]},{"__typename":"PlayByPlayGenericSport","clock":"","teamId":42767,"plays":[{"__typename":"GenericPlay","playText":"Hobbs, K. to 1b.","homeScore":null,"visitorScore":null,"clock":""}]},{"__typename":"PlayByPlayGenericSport","clock":"","teamId":42767,"plays":[{"__typename":"GenericPlay","playText":"Hobbs, Ki. to 3b.","homeScore":null,"visitorScore":null,"clock":""}]},{"__typename":"PlayByPlayGenericSport","clock":"","teamId":41871,"plays":[{"__typename":"GenericPlay","playText":"KYSER, M. grounded out to 3b (3-2 KBSFBB).","homeScore":null,"visitorScore":null,"clock":""}]},{"__typename":"PlayByPlayGenericSport","clock":"","teamId":41871,"plays":[{"__typename":"GenericPlay","playText":"BUFFINGTON,H homered to center field, RBI (0-2 FS).","homeScore":null,"visitorScore":null,"clock":""}]},{"__typename":"PlayByPlayGenericSport","clock":"","teamId":41871,"plays":[{"__typename":"GenericPlay","playText":"PHILLIPS, A. homered to left center, RBI (1-1 KB).","homeScore":null,"visitorScore":null,"clock":""}]},{"__typename":"PlayByPlayGenericSport","clock":"","teamId":41871,"plays":[{"__typename":"GenericPlay","playText":"PATE, E. grounded out to ss.","homeScore":null,"visitorScore":null,"clock":""}]},{"__typename":"PlayByPlayGenericSport","clock":"","teamId":41871,"plays":[{"__typename":"GenericPlay","playText":"NICHOLSON, K popped up to ss (0-0).","homeScore":null,"visitorScore":null,"clock":""}]},{"__typename":"PlayByPlayGenericSport","clock":"","teamId":41871,"plays":[{"__typename":"GenericPlay","playText":"Batting ends R: 2 H:2 E:0","homeScore":1,"visitorScore":3,"clock":""}]},{"__typename":"PlayByPlayGenericSport","clock":"","teamId":42767,"plays":[{"__typename":"GenericPlay","playText":"Batting starts","homeScore":null,"visitorScore":null,"clock":""}]},{"__typename":"PlayByPlayGenericSport","clock":"","teamId":42767,"plays":[{"__typename":"GenericPlay","playText":"Hobbs, K. struck out swinging (1-2 FFBS).","homeScore":null,"visitorScore":null,"clock":""}]},{"__typename":"PlayByPlayGenericSport","clock":"","teamId":42767,"plays":[{"__typename":"GenericPlay","playText":"Mountain, H. fouled out to c (2-2 BFKB).","homeScore":null,"visitorScore":null,"clock":""}]},{"__typename":"PlayByPlayGenericSport","clock":"","teamId":42767,"plays":[{"__typename":"GenericPlay","playText":"Scheaffer, H popped up to 2b (2-1 BBF).","homeScore":null,"visitorScore":null,"clock":""}]},{"__typename":"PlayByPlayGenericSport","clock":"","teamId":42767,"plays":[{"__typename":"GenericPlay","playText":"Batting ends R: 0 H:0 E:0","homeScore":1,"visitorScore":3,"clock":""}]}]},{"__typename":"PlayByPlayDetails","periodNumber":5,"periodDisplay":"5th","playbyplayStats":[{"__typename":"PlayByPlayGenericSport","clock":"","teamId":41871,"plays":[{"__typename":"GenericPlay","playText":"Batting starts","homeScore":null,"visitorScore":null,"clock":""}]},{"__typename":"PlayByPlayGenericSport","clock":"","teamId":42767,"plays":[{"__typename":"GenericPlay","playText":"Grams, D. to p for Vento, M..","homeScore":null,"visitorScore":null,"clock":""}]},{"__typename":"PlayByPlayGenericSport","clock":"","teamId":41871,"plays":[{"__typename":"GenericPlay","playText":"JONES, E. doubled to center field (0-0).","homeScore":null,"visitorScore":null,"clock":""}]},{"__typename":"PlayByPlayGenericSport","clock":"","teamId":41871,"plays":[{"__typename":"GenericPlay","playText":"NOWAKOWSKI,M reached on a fielder's choice (1-2 KFB).","homeScore":null,"visitorScore":null,"clock":""}]},{"__typename":"PlayByPlayGenericSport","clock":"","teamId":41871,"plays":[{"__typename":"GenericPlay","playText":"REED, A. struck out swinging (3-2 BKBBKS).","homeScore":null,"visitorScore":null,"clock":""}]},{"__typename":"PlayByPlayGenericSport","clock":"","teamId":41871,"plays":[{"__typename":"GenericPlay","playText":"RASMUSSEN M singled up the middle, RBI (0-0); NOWAKOWSKI,M advanced to second; JONES, E. scored.","homeScore":null,"visitorScore":null,"clock":""}]},{"__typename":"PlayByPlayGenericSport","clock":"","teamId":41871,"plays":[{"__typename":"GenericPlay","playText":"KYSER, M. struck out swinging (1-2 KKBFS).","homeScore":null,"visitorScore":null,"clock":""}]},{"__typename":"PlayByPlayGenericSport","clock":"","teamId":41871,"plays":[{"__typename":"GenericPlay","playText":"BUFFINGTON,H walked (3-0 BBBB); RASMUSSEN M advanced to second; NOWAKOWSKI,M advanced to third.","homeScore":null,"visitorScore":null,"clock":""}]},{"__typename":"PlayByPlayGenericSport","clock":"","teamId":41871,"plays":[{"__typename":"GenericPlay","playText":"PHILLIPS, A. fouled out to 1b (2-1 BKB).","homeScore":null,"visitorScore":null,"clock":""}]},{"__typename":"PlayByPlayGenericSport","clock":"","teamId":41871,"plays":[{"__typename":"GenericPlay","playText":"Batting ends R: 1 H:2 E:0","homeScore":1,"visitorScore":4,"clock":""}]},{"__typename":"PlayByPlayGenericSport","clock":"","teamId":42767,"plays":[{"__typename":"GenericPlay","playText":"Batting starts","homeScore":null,"visitorScore":null,"clock":""}]},{"__typename":"PlayByPlayGenericSport","clock":"","teamId":41871,"plays":[{"__typename":"GenericPlay","playText":"LIVELY, C. to c for KYSER, M..","homeScore":null,"visitorScore":null,"clock":""}]},{"__typename":"PlayByPlayGenericSport","clock":"","teamId":42767,"plays":[{"__typename":"GenericPlay","playText":"Hobbs, Ki. walked (3-2 BBFBKB).","homeScore":null,"visitorScore":null,"clock":""}]},{"__typename":"PlayByPlayGenericSport","clock":"","teamId":42767,"plays":[{"__typename":"GenericPlay","playText":"Talbot, C. singled to third base, bunt (0-0); Hobbs, Ki. advanced to second.","homeScore":null,"visitorScore":null,"clock":""}]},{"__typename":"PlayByPlayGenericSport","clock":"","teamId":42767,"plays":[{"__typename":"GenericPlay","playText":"Grill, E. doubled to left center, RBI (1-2 KFFFFBF); Talbot, C. advanced to third; Hobbs, Ki. scored.","homeScore":null,"visitorScore":null,"clock":""}]},{"__typename":"PlayByPlayGenericSport","clock":"","teamId":42767,"plays":[{"__typename":"GenericPlay","playText":"Hebel, E. to 2b for Carter, H..","homeScore":null,"visitorScore":null,"clock":""}]},{"__typename":"PlayByPlayGenericSport","clock":"","teamId":42767,"plays":[{"__typename":"GenericPlay","playText":"Hebel, E. walked (3-0 BBBB).","homeScore":null,"visitorScore":null,"clock":""}]},{"__typename":"PlayByPlayGenericSport","clock":"","teamId":42767,"plays":[{"__typename":"GenericPlay","playText":"Yarotsky, T. reached on a fielder's choice (1-0 B); Hebel, E. advanced to second; Grill, E. advanced to third; Talbot, C. out at home 3b to c.","homeScore":null,"visitorScore":null,"clock":""}]},{"__typename":"PlayByPlayGenericSport","clock":"","teamId":42767,"plays":[{"__typename":"GenericPlay","playText":"Herzinger reached on a fielder's choice (1-1 BF); Yarotsky, T. advanced to second; Hebel, E. advanced to third; Grill, E. out at home 1b to c.","homeScore":null,"visitorScore":null,"clock":""}]},{"__typename":"PlayByPlayGenericSport","clock":"","teamId":42767,"plays":[{"__typename":"GenericPlay","playText":"Hobbs, K. lined out to rf (1-2 FFFB).","homeScore":null,"visitorScore":null,"clock":""}]},{"__typename":"PlayByPlayGenericSport","clock":"","teamId":42767,"plays":[{"__typename":"GenericPlay","playText":"Batting ends R: 1 H:2 E:0","homeScore":2,"visitorScore":4,"clock":""}]}]},{"__typename":"PlayByPlayDetails","periodNumber":6,"periodDisplay":"6th","playbyplayStats":[{"__typename":"PlayByPlayGenericSport","clock":"","teamId":41871,"plays":[{"__typename":"GenericPlay","playText":"Batting starts","homeScore":null,"visitorScore":null,"clock":""}]},{"__typename":"PlayByPlayGenericSport","clock":"","teamId":42767,"plays":[{"__typename":"GenericPlay","playText":"Hebel, E. to 1b.","homeScore":null,"visitorScore":null,"clock":""}]},{"__typename":"PlayByPlayGenericSport","clock":"","teamId":42767,"plays":[{"__typename":"GenericPlay","playText":"Hobbs, K. to 3b.","homeScore":null,"visitorScore":null,"clock":""}]},{"__typename":"PlayByPlayGenericSport","clock":"","teamId":42767,"plays":[{"__typename":"GenericPlay","playText":"Hobbs, Ki. to 2b.","homeScore":null,"visitorScore":null,"clock":""}]},{"__typename":"PlayByPlayGenericSport","clock":"","teamId":41871,"plays":[{"__typename":"GenericPlay","playText":"PATE, E. popped up to 3b (0-0).","homeScore":null,"visitorScore":null,"clock":""}]},{"__typename":"PlayByPlayGenericSport","clock":"","teamId":41871,"plays":[{"__typename":"GenericPlay","playText":"NICHOLSON, K grounded out to 3b (0-1 K).","homeScore":null,"visitorScore":null,"clock":""}]},{"__typename":"PlayByPlayGenericSport","clock":"","teamId":41871,"plays":[{"__typename":"GenericPlay","playText":"JONES, E. flied out to lf (2-1 SBB).","homeScore":null,"visitorScore":null,"clock":""}]},{"__typename":"PlayByPlayGenericSport","clock":"","teamId":41871,"plays":[{"__typename":"GenericPlay","playText":"Batting ends R: 0 H:0 E:0","homeScore":2,"visitorScore":4,"clock":""}]},{"__typename":"PlayByPlayGenericSport","clock":"","teamId":42767,"plays":[{"__typename":"GenericPlay","playText":"Batting starts","homeScore":null,"visitorScore":null,"clock":""}]},{"__typename":"PlayByPlayGenericSport","clock":"","teamId":42767,"plays":[{"__typename":"GenericPlay","playText":"Mountain, H. singled to center field (0-0).","homeScore":null,"visitorScore":null,"clock":""}]},{"__typename":"PlayByPlayGenericSport","clock":"","teamId":42767,"plays":[{"__typename":"GenericPlay","playText":"Scheaffer, H out at first c to 2b, SAC, bunt (0-0); Mountain, H. advanced to second.","homeScore":null,"visitorScore":null,"clock":""}]},{"__typename":"PlayByPlayGenericSport","clock":"","teamId":42767,"plays":[{"__typename":"GenericPlay","playText":"Saville, A. pinch hit for Hobbs, Ki..","homeScore":null,"visitorScore":null,"clock":""}]},{"__typename":"PlayByPlayGenericSport","clock":"","teamId":42767,"plays":[{"__typename":"GenericPlay","playText":"Saville, A. popped up to ss (1-1 BF).","homeScore":null,"visitorScore":null,"clock":""}]},{"__typename":"PlayByPlayGenericSport","clock":"","teamId":42767,"plays":[{"__typename":"GenericPlay","playText":"Talbot, C. flied out to cf (1-1 FB).","homeScore":null,"visitorScore":null,"clock":""}]},{"__typename":"PlayByPlayGenericSport","clock":"","teamId":42767,"plays":[{"__typename":"GenericPlay","playText":"Batting ends R: 0 H:1 E:0","homeScore":2,"visitorScore":4,"clock":""}]}]},{"__typename":"PlayByPlayDetails","periodNumber":7,"periodDisplay":"7th","playbyplayStats":[{"__typename":"PlayByPlayGenericSport","clock":"","teamId":41871,"plays":[{"__typename":"GenericPlay","playText":"Batting starts","homeScore":null,"visitorScore":null,"clock":""}]},{"__typename":"PlayByPlayGenericSport","clock":"","teamId":42767,"plays":[{"__typename":"GenericPlay","playText":"Saville, A. to 2b.","homeScore":null,"visitorScore":null,"clock":""}]},{"__typename":"PlayByPlayGenericSport","clock":"","teamId":42767,"plays":[{"__typename":"GenericPlay","playText":"Herzinger to c.","homeScore":null,"visitorScore":null,"clock":""}]},{"__typename":"PlayByPlayGenericSport","clock":"","teamId":42767,"plays":[{"__typename":"GenericPlay","playText":"Scheaffer, H to dp.","homeScore":null,"visitorScore":null,"clock":""}]},{"__typename":"PlayByPlayGenericSport","clock":"","teamId":41871,"plays":[{"__typename":"GenericPlay","playText":"NOWAKOWSKI,M singled to center field (2-2 BFFB).","homeScore":null,"visitorScore":null,"clock":""}]},{"__typename":"PlayByPlayGenericSport","clock":"","teamId":41871,"plays":[{"__typename":"GenericPlay","playText":"REED, A. grounded out to c, SAC, bunt (0-0); NOWAKOWSKI,M advanced to second.","homeScore":null,"visitorScore":null,"clock":""}]},{"__typename":"PlayByPlayGenericSport","clock":"","teamId":41871,"plays":[{"__typename":"GenericPlay","playText":"RASMUSSEN M flied out to lf (1-1 BS).","homeScore":null,"visitorScore":null,"clock":""}]},{"__typename":"PlayByPlayGenericSport","clock":"","teamId":41871,"plays":[{"__typename":"GenericPlay","playText":"NOWAKOWSKI,M advanced to third on a wild pitch.","homeScore":null,"visitorScore":null,"clock":""}]},{"__typename":"PlayByPlayGenericSport","clock":"","teamId":41871,"plays":[{"__typename":"GenericPlay","playText":"LIVELY, C. singled through the left side, RBI (1-2 KBK); NOWAKOWSKI,M scored.","homeScore":null,"visitorScore":null,"clock":""}]},{"__typename":"PlayByPlayGenericSport","clock":"","teamId":41871,"plays":[{"__typename":"GenericPlay","playText":"BUFFINGTON,H struck out swinging (3-2 BKFFBBS).","homeScore":null,"visitorScore":null,"clock":""}]},{"__typename":"PlayByPlayGenericSport","clock":"","teamId":41871,"plays":[{"__typename":"GenericPlay","playText":"Batting ends R: 1 H:2 E:0","homeScore":2,"visitorScore":5,"clock":""}]},{"__typename":"PlayByPlayGenericSport","clock":"","teamId":42767,"plays":[{"__typename":"GenericPlay","playText":"Batting starts","homeScore":null,"visitorScore":null,"clock":""}]},{"__typename":"PlayByPlayGenericSport","clock":"","teamId":42767,"plays":[{"__typename":"GenericPlay","playText":"Grill, E. grounded out to 2b (0-1 F).","homeScore":null,"visitorScore":null,"clock":""}]},{"__typename":"PlayByPlayGenericSport","clock":"","teamId":42767,"plays":[{"__typename":"GenericPlay","playText":"Hebel, E. homered to left field, RBI (2-0 BB).","homeScore":null,"visitorScore":null,"clock":""}]},{"__typename":"PlayByPlayGenericSport","clock":"","teamId":42767,"plays":[{"__typename":"GenericPlay","playText":"Robison, J. pinch hit for Yarotsky, T..","homeScore":null,"visitorScore":null,"clock":""}]},{"__typename":"PlayByPlayGenericSport","clock":"","teamId":42767,"plays":[{"__typename":"GenericPlay","playText":"Robison, J. struck out swinging (1-2 KKBFS).","homeScore":null,"visitorScore":null,"clock":""}]},{"__typename":"PlayByPlayGenericSport","clock":"","teamId":42767,"plays":[{"__typename":"GenericPlay","playText":"Herzinger lined out to p (2-1 BFB).","homeScore":null,"visitorScore":null,"clock":""}]},{"__typename":"PlayByPlayGenericSport","clock":"","teamId":42767,"plays":[{"__typename":"GenericPlay","playText":"Batting ends R: 1 H:1 E:0","homeScore":3,"visitorScore":5,"clock":""}]}]}]}